datasets/__init__.py
datasets/example.py
ml_holmes-0.0.1.dist-info/LICENSE
ml_holmes-0.0.1.dist-info/METADATA
ml_holmes-0.0.1.dist-info/WHEEL
ml_holmes-0.0.1.dist-info/top_level.txt
ml_holmes-0.0.1.dist-info/RECORD
