Metadata-Version: 2.1
Name: ml-holmes
Version: 0.0.1
Summary: A machine learning benchmark on tabular data
Home-page: https://github.com/sedol1339/holmes
Author: Oleg Sedukhin
Author-email: sedol.mong@mail.ru
License: UNKNOWN
Platform: UNKNOWN
Classifier: Programming Language :: Python :: 3
Classifier: License :: OSI Approved :: MIT License
Classifier: Operating System :: OS Independent
Requires-Python: >=3.6
License-File: LICENSE
